roop_redshift/__init__.py
roop_redshift/redshift.py
roop_redshift-0.0.4.dist-info/METADATA
roop_redshift-0.0.4.dist-info/WHEEL
roop_redshift-0.0.4.dist-info/top_level.txt
roop_redshift-0.0.4.dist-info/RECORD
